edelweiss_data/__init__.py
edelweiss_data/__main__.py
edelweiss_data/api.py
edelweiss_data/cli/__main__.py
edelweiss_data/cli/auth.py
edelweiss_data/cli/create.py
edelweiss_data/cli/inprogress_delete.py
edelweiss_data/cli/inprogress_get.py
edelweiss_data/cli/inprogress_publish.py
edelweiss_data/cli/inprogress_update.py
edelweiss_data/cli/permissions.py
edelweiss_data/cli/published_delete.py
edelweiss_data/cli/published_get.py
edelweiss_data/cli/published_list.py
edelweiss_data/cli/published_newversion.py
edelweiss_data/server.py
edelweiss_data/utils.py
edelweiss_data-0.2.19.dist-info/LICENSE
edelweiss_data-0.2.19.dist-info/WHEEL
edelweiss_data-0.2.19.dist-info/METADATA
edelweiss_data-0.2.19.dist-info/RECORD
