Metadata-Version: 2.1
Name: edelweiss-data
Version: 0.2.19
Summary: Python client for EdelweissData
Home-page: https://github.com/DouglasConnect/edelweiss-data-python
Author: Edelweiss Connect
Author-email: info@edelweissconnect.com
Requires-Python: >=3.6,<4.0
Classifier: Programming Language :: Python :: 3
Classifier: Programming Language :: Python :: 3.6
Classifier: Programming Language :: Python :: 3.7
Classifier: Programming Language :: Python :: 3.8
Requires-Dist: docopt (>=0.6.2,<0.7.0)
Requires-Dist: iso8601 (>=0.1.11)
Requires-Dist: pandas (>=0.23.0)
Requires-Dist: pyjwt (>=1.5.3,<2.0.0)
Requires-Dist: requests (>=2.18.4,<3.0.0)
Project-URL: Documentation, https://github.com/DouglasConnect/edelweiss-data-python
Project-URL: Repository, https://github.com/DouglasConnect/edelweiss-data-python
